search_query_finder/__init__.py
search_query_finder/find_query.py
search_query_finder-0.0.12.dist-info/LICENSE
search_query_finder-0.0.12.dist-info/METADATA
search_query_finder-0.0.12.dist-info/WHEEL
search_query_finder-0.0.12.dist-info/top_level.txt
search_query_finder-0.0.12.dist-info/RECORD
