Metadata-Version: 2.1
Name: search-query-finder
Version: 0.0.12
Summary: A general function that extracts a search query from spoken text given search terms to look out for.
Home-page: https://github.com/Omarzintan/search_query_finder_package
Author: Omar Zintan Mwinila-Yuori
Author-email: zintanomar@gmail.com
License: UNKNOWN
Project-URL: Bug Tracker, https://github.com/Omarzintan/search_query_finder_package/issues
Platform: UNKNOWN
Classifier: Programming Language :: Python :: 3
Classifier: License :: OSI Approved :: MIT License
Classifier: Operating System :: OS Independent
Requires-Python: >=3.6
License-File: LICENSE
Requires-Dist: nltk (==3.6.7)
